botblend/__init__.py
botblend/msgraph.py
botblend/sharepoint.py
botblend-0.0.4.dist-info/METADATA
botblend-0.0.4.dist-info/WHEEL
botblend-0.0.4.dist-info/top_level.txt
botblend-0.0.4.dist-info/RECORD
