Metadata-Version: 2.4
Name: botblend
Version: 0.0.4
Summary: Librería de utilerías para automatizaciones RPA con Microsoft Graph y otras herramientas.
Home-page: https://github.com/raulsanvaz/botblend
Author: Raul Sanz
Author-email: mail@rulosanz.com
Project-URL: Documentation, https://github.com/raulsanvaz/botblend#readme
Project-URL: Source, https://github.com/raulsanvaz/botblend
Classifier: Development Status :: 3 - Alpha
Classifier: Intended Audience :: Developers
Classifier: Topic :: Software Development :: Libraries
Classifier: License :: OSI Approved :: MIT License
Classifier: Programming Language :: Python :: 3
Classifier: Programming Language :: Python :: 3.10
Classifier: Operating System :: OS Independent
Requires-Python: >=3.10
Requires-Dist: msal>=1.0.0
Requires-Dist: requests>=2.0.0
Requires-Dist: python-dotenv>=1.0.0
Requires-Dist: pandas>=1.0.0
Requires-Dist: openpyxl>=3.0.0
Requires-Dist: Office365-REST-Python-Client==2.3.11
Dynamic: author
Dynamic: author-email
Dynamic: classifier
Dynamic: description
Dynamic: description-content-type
Dynamic: home-page
Dynamic: project-url
Dynamic: requires-dist
Dynamic: requires-python
Dynamic: summary
